beetle_image_compressor/__init__.py
Beetle_Image_Compressor-0.1.0.dist-info/WHEEL
Beetle_Image_Compressor-0.1.0.dist-info/DESCRIPTION.rst
Beetle_Image_Compressor-0.1.0.dist-info/RECORD
Beetle_Image_Compressor-0.1.0.dist-info/METADATA
Beetle_Image_Compressor-0.1.0.dist-info/metadata.json
Beetle_Image_Compressor-0.1.0.dist-info/top_level.txt
