Metadata-Version: 2.0
Name: Beetle-Image-Compressor
Version: 0.1.0
Summary: Auto image compressor for Beetle
Home-page: https://github.com/cknv/beetle-image-compressor
Author: Esben Sonne
Author-email: esbensonne+code@gmail.com
License: MIT
Platform: UNKNOWN
Classifier: Environment :: Plugins
Classifier: Environment :: Console
Classifier: Development Status :: 3 - Alpha
Classifier: Intended Audience :: Developers
Classifier: License :: OSI Approved :: MIT License
Classifier: Programming Language :: Python :: 3
Requires-Dist: Pillow
